{
    "fetch_date": "2023/11/15 15:20:41",
    "releases": [
        {
            "model": "SM-G781B",
            "version": "G781BXXS8HWI3",
            "description": "SM-G781B_EUR_13_Opensource.zip"
        },
        {
            "model": "SM-G780G",
            "version": "G780GXXS7EWI3",
            "description": "SM-G780G_CIS_13_Opensource.zip"
        },
        {
            "model": "SM-T505",
            "version": "T505XXS6CWI3",
            "description": "SM-T505_SEA_12_Opensource.zip"
        },
        {
            "model": "SM-G981B",
            "version": "G981BXXUIHWH9",
            "description": "SM-G981B_13_Opensource.zip, SM-G981B_13_Opensource_G981BXXSIHWI7.zip"
        },
        {
            "model": "SM-G986B",
            "version": "G986BXXUIHWH9",
            "description": "SM-G986B_13_Opensource.zip, SM-G986B_13_Opensource_G986BXXSIHWI7.zip"
        },
        {
            "model": "SM-T505C",
            "version": "T505CZCU3CVF1",
            "description": "SM-T505C_CHN_12_Opensource.zip"
        },
        {
            "model": "SM-A528B",
            "version": "A528BZTS5EWJ1",
            "description": "SM-A528B_TW_13_Opensource.zip"
        },
        {
            "model": "SM-G988B",
            "version": "G988BXXUIHWH9",
            "description": "SM-G988B_13_Opensource.zip, SM-G988B_13_Opensource_G988BXXSIHWI7.zip"
        },
        {
            "model": "SM-S918U",
            "version": "S918USQU1BWJM",
            "description": "SM-S918U_NA_14_Opensource.zip"
        },
        {
            "model": "SM-S916U",
            "version": "S916USQU1BWJM",
            "description": "SM-S916U_NA_14_Opensource.zip"
        }
    ]
}