{
    "fetch_date": "2023/09/15 08:10:42",
    "releases": [
        {
            "model": "SM-X900",
            "version": "X900XXU5BWH6",
            "description": "SM-X900_EUR_13_Opensource.zip"
        },
        {
            "model": "SM-A217F",
            "version": "A217FXXS9DWF1",
            "description": "SM-A217F_CIS_12_Opensource.zip"
        },
        {
            "model": "SM-M536B",
            "version": "M536BXXU1BVK4",
            "description": "SM-M536B_LATIN_13_Opensource.zip"
        },
        {
            "model": "SM-G988N",
            "version": "G988NKSU3IWH9",
            "description": "SM-G988N_KOR_13_Opensource.zip"
        },
        {
            "model": "SM-A135N",
            "version": "A135NKSU2AVI3",
            "description": "SM-A135N_KOR_12_Opensource.zip"
        },
        {
            "model": "SM-A315N",
            "version": "A315NKSU3DWF1",
            "description": "SM-A315N_KOR_12_Opensource.zip"
        },
        {
            "model": "SM-J610F",
            "version": "J610FXXS8CVL1",
            "description": "SM-J610F_SWA_QQ_Opensource.zip"
        },
        {
            "model": "SM-A135N",
            "version": "A135NKSU5CWH3",
            "description": "SM-A135N_KOR_13_Opensource.zip"
        },
        {
            "model": "SM-S911N",
            "version": "S911NKSU2AWGJ",
            "description": "SM-S911N_KOR_13_Opensource.zip"
        },
        {
            "model": "SM-A546E",
            "version": "A546EXXU5AWGJ",
            "description": "SM-A546E_SEA_13_Opensource.zip"
        }
    ]
}